fast_pauli/__init__.py
fast_pauli/__version__.py
fast_pauli/_fast_pauli.cpython-312-aarch64-linux-gnu.so
fast_pauli/qiskit_helpers.py
fast_pauli/cpp/examples/01_pauli_op.cpp
fast_pauli/cpp/examples/02_pauli_op_multistate.cpp
fast_pauli/cpp/examples/03_summed_pauli_op.cpp
fast_pauli/cpp/examples/04_get_sparse_repr.cpp
fast_pauli/cpp/examples/05_summed_pauli_op_sq.cpp
fast_pauli/cpp/examples/CMakeLists.txt
fast_pauli/cpp/include/README.md
fast_pauli/cpp/include/__factory.hpp
fast_pauli/cpp/include/__nb_helpers.hpp
fast_pauli/cpp/include/__pauli.hpp
fast_pauli/cpp/include/__pauli_helpers.hpp
fast_pauli/cpp/include/__pauli_op.hpp
fast_pauli/cpp/include/__pauli_string.hpp
fast_pauli/cpp/include/__summed_pauli_op.hpp
fast_pauli/cpp/include/__type_traits.hpp
fast_pauli/cpp/include/fast_pauli.hpp
fast_pauli/cpp/src/CMakeLists.txt
fast_pauli/cpp/src/fast_pauli.cpp
fast_pauli/cpp/src/include/__pauli_bindings.hpp
fast_pauli/cpp/src/include/__pauli_op_bindings.hpp
fast_pauli/cpp/src/include/__pauli_string_bindings.hpp
fast_pauli/cpp/src/include/__summed_pauli_op_bindings.hpp
fast_pauli/cpp/src/include/__types.hpp
fast_pauli/cpp/tests/CMakeLists.txt
fast_pauli/cpp/tests/test_factory.cpp
fast_pauli/cpp/tests/test_pauli.cpp
fast_pauli/cpp/tests/test_pauli_helpers.cpp
fast_pauli/cpp/tests/test_pauli_op.cpp
fast_pauli/cpp/tests/test_pauli_string.cpp
fast_pauli/cpp/tests/test_summed_pauli_op.cpp
fast_pauli/pypauli/__init__.py
fast_pauli/pypauli/helpers.py
fast_pauli/pypauli/pauli_op.py
fast_pauli/pypauli/pauli_string.py
fast_pauli.libs/libgomp-d22c30c5.so.1.0.0
fast_pauli-0.0.35.dist-info/METADATA
fast_pauli-0.0.35.dist-info/WHEEL
fast_pauli-0.0.35.dist-info/RECORD
fast_pauli-0.0.35.dist-info/licenses/LICENSE.txt
