Metadata-Version: 2.2
Name: fast_pauli
Version: 0.0.35
Summary: fast pauli
Author-Email: "James E. T. Smith" <james.smith@qognitive.io>, Eugene Rublenko <eugene.rublenko@qognitive.io>, Alex Lerner <alex.lerner@qognitive.io>, Sebastien Roy <sebastien.roy@qognitive.io>, Jeffrey Berger <jeff.berger@qognitive.io>
Classifier: Programming Language :: Python :: 3 :: Only
Classifier: Programming Language :: Python :: 3.10
Classifier: Programming Language :: Python :: 3.11
Classifier: Programming Language :: Python :: 3.12
Requires-Python: >=3.10
Requires-Dist: numpy
Requires-Dist: qiskit
Requires-Dist: qiskit-algorithms
Provides-Extra: dev
Requires-Dist: cibuildwheel; extra == "dev"
Requires-Dist: clang-format; extra == "dev"
Requires-Dist: cmake-format; extra == "dev"
Requires-Dist: pre-commit; extra == "dev"
Requires-Dist: mypy; extra == "dev"
Requires-Dist: ruff; extra == "dev"
Requires-Dist: pytest; extra == "dev"
Requires-Dist: pytest-benchmark; extra == "dev"
Requires-Dist: setuptools_scm; extra == "dev"
Requires-Dist: sphinx; extra == "dev"
Requires-Dist: sphinx_rtd_theme; extra == "dev"
Requires-Dist: sphinx-autobuild; extra == "dev"
Provides-Extra: docs
Requires-Dist: cmake>=3.25; extra == "docs"
Requires-Dist: sphinx; extra == "docs"
Requires-Dist: sphinx-rtd-theme; extra == "docs"
Requires-Dist: sphinx-copybutton; extra == "docs"
Requires-Dist: sphinx-autobuild; extra == "docs"
Requires-Dist: sphinxcontrib-napoleon; extra == "docs"
Requires-Dist: breathe; extra == "docs"
Requires-Dist: furo; extra == "docs"
Provides-Extra: examples
